congenial_pogato/command_templates.py
congenial_pogato/db.py
congenial_pogato/encoder.py
congenial_pogato/parse.py
congenial_pogato/schema.py
congenial_pogato/table.py
congenial_pogato/util.py
congenial_pogato-0.0.1a0.dist-info/WHEEL
congenial_pogato-0.0.1a0.dist-info/METADATA
congenial_pogato-0.0.1a0.dist-info/RECORD
