Metadata-Version: 2.1
Name: congenial-pogato
Version: 0.0.1a0
Summary: Convenience wrapper psycopg
License: Martian Law
Author: Andrew Rainboldt
Author-email: arainboldt@protonmail.com
Requires-Python: >=3.8,<4.0
Classifier: License :: Other/Proprietary License
Classifier: Programming Language :: Python :: 3
Classifier: Programming Language :: Python :: 3.8
Classifier: Programming Language :: Python :: 3.9
Requires-Dist: pandas
Requires-Dist: psycopg2-binary (>=2.8.6,<3.0.0)
